PortscannerGtk/__init__.py
PortscannerGtk-0.1.1.dist-info/LICENCE
PortscannerGtk-0.1.1.dist-info/METADATA
PortscannerGtk-0.1.1.dist-info/WHEEL
PortscannerGtk-0.1.1.dist-info/top_level.txt
PortscannerGtk-0.1.1.dist-info/RECORD
