Metadata-Version: 2.1
Name: PortscannerGtk
Version: 0.1.1
Summary: This is a multithreading Portscanner with Gtk4 GUI.
Author-email: Lennart Martens <monkeynator78@gmail.com>
License: BSD-3-Clause
Project-URL: Repository, https://github.com/Lennart1978/Multithreading_PortscannerGtk
Requires-Python: >=3.7
License-File: LICENCE
Requires-Dist: PyGObject (==3.44.1) ; python_version < "3.8"
